[
    {
        "exp": 0,
        "strength": 0,
        "agility": 0,
        "intelligence": 0,
        "luck": 0,
        "HP": 0,
        "MP": 0,
        "battleAction1": 0,
        "battleAction2": 0,
        "battleAction3": 0,
        "battleAction4": 0,
        "normalAction1": 0,
        "normalAction2": 0,
        "normalAction3": 0,
        "normalAction4": 0,
        "vitality": 0,
        "level": 0,
        "dummy0": 255
    },
    {
        "exp": 0,
        "strength": 80,
        "agility": 57,
        "intelligence": 40,
        "luck": 25,
        "HP": 99,
        "MP": 9,
        "battleAction1": 0,
        "battleAction2": 0,
        "battleAction3": 0,
        "battleAction4": 0,
        "normalAction1": 0,
        "normalAction2": 0,
        "normalAction3": 0,
        "normalAction4": 0,
        "vitality": 87,
        "level": 1,
        "dummy0": 255
    },
    {
        "exp": 220,
        "strength": 81,
        "agility": 58,
        "intelligence": 41,
        "luck": 26,
        "HP": 101,
        "MP": 13,
        "battleAction1": 0,
        "battleAction2": 0,
        "battleAction3": 0,
        "battleAction4": 0,
        "normalAction1": 0,
        "normalAction2": 0,
        "normalAction3": 0,
        "normalAction4": 0,
        "vitality": 87,
        "level": 2,
        "dummy0": 255
    },
    {
        "exp": 962,
        "strength": 82,
        "agility": 59,
        "intelligence": 42,
        "luck": 27,
        "HP": 104,
        "MP": 17,
        "battleAction1": 0,
        "battleAction2": 0,
        "battleAction3": 0,
        "battleAction4": 0,
        "normalAction1": 0,
        "normalAction2": 0,
        "normalAction3": 0,
        "normalAction4": 0,
        "vitality": 87,
        "level": 3,
        "dummy0": 255
    },
    {
        "exp": 3474,
        "strength": 83,
        "agility": 60,
        "intelligence": 43,
        "luck": 28,
        "HP": 107,
        "MP": 21,
        "battleAction1": 29,
        "battleAction2": 101,
        "battleAction3": 0,
        "battleAction4": 0,
        "normalAction1": 0,
        "normalAction2": 0,
        "normalAction3": 0,
        "normalAction4": 0,
        "vitality": 87,
        "level": 4,
        "dummy0": 255
    },
    {
        "exp": 5986,
        "strength": 85,
        "agility": 62,
        "intelligence": 45,
        "luck": 30,
        "HP": 110,
        "MP": 25,
        "battleAction1": 0,
        "battleAction2": 0,
        "battleAction3": 0,
        "battleAction4": 0,
        "normalAction1": 0,
        "normalAction2": 0,
        "normalAction3": 0,
        "normalAction4": 0,
        "vitality": 87,
        "level": 5,
        "dummy0": 255
    },
    {
        "exp": 8497,
        "strength": 86,
        "agility": 62,
        "intelligence": 46,
        "luck": 32,
        "HP": 113,
        "MP": 26,
        "battleAction1": 19,
        "battleAction2": 0,
        "battleAction3": 0,
        "battleAction4": 0,
        "normalAction1": 0,
        "normalAction2": 0,
        "normalAction3": 0,
        "normalAction4": 0,
        "vitality": 87,
        "level": 6,
        "dummy0": 255
    },
    {
        "exp": 11009,
        "strength": 87,
        "agility": 63,
        "intelligence": 48,
        "luck": 35,
        "HP": 116,
        "MP": 28,
        "battleAction1": 0,
        "battleAction2": 0,
        "battleAction3": 0,
        "battleAction4": 0,
        "normalAction1": 0,
        "normalAction2": 0,
        "normalAction3": 0,
        "normalAction4": 0,
        "vitality": 87,
        "level": 7,
        "dummy0": 255
    },
    {
        "exp": 13521,
        "strength": 89,
        "agility": 63,
        "intelligence": 49,
        "luck": 37,
        "HP": 120,
        "MP": 29,
        "battleAction1": 0,
        "battleAction2": 0,
        "battleAction3": 0,
        "battleAction4": 0,
        "normalAction1": 0,
        "normalAction2": 0,
        "normalAction3": 0,
        "normalAction4": 0,
        "vitality": 87,
        "level": 8,
        "dummy0": 255
    },
    {
        "exp": 16033,
        "strength": 90,
        "agility": 64,
        "intelligence": 51,
        "luck": 40,
        "HP": 123,
        "MP": 31,
        "battleAction1": 0,
        "battleAction2": 0,
        "battleAction3": 0,
        "battleAction4": 0,
        "normalAction1": 0,
        "normalAction2": 0,
        "normalAction3": 0,
        "normalAction4": 0,
        "vitality": 87,
        "level": 9,
        "dummy0": 255
    },
    {
        "exp": 19178,
        "strength": 92,
        "agility": 65,
        "intelligence": 53,
        "luck": 43,
        "HP": 127,
        "MP": 33,
        "battleAction1": 0,
        "battleAction2": 0,
        "battleAction3": 0,
        "battleAction4": 0,
        "normalAction1": 0,
        "normalAction2": 0,
        "normalAction3": 0,
        "normalAction4": 0,
        "vitality": 87,
        "level": 10,
        "dummy0": 255
    },
    {
        "exp": 23114,
        "strength": 93,
        "agility": 65,
        "intelligence": 54,
        "luck": 46,
        "HP": 132,
        "MP": 36,
        "battleAction1": 27,
        "battleAction2": 0,
        "battleAction3": 0,
        "battleAction4": 0,
        "normalAction1": 0,
        "normalAction2": 0,
        "normalAction3": 0,
        "normalAction4": 0,
        "vitality": 87,
        "level": 11,
        "dummy0": 255
    },
    {
        "exp": 28039,
        "strength": 94,
        "agility": 66,
        "intelligence": 56,
        "luck": 49,
        "HP": 138,
        "MP": 39,
        "battleAction1": 0,
        "battleAction2": 0,
        "battleAction3": 0,
        "battleAction4": 0,
        "normalAction1": 0,
        "normalAction2": 0,
        "normalAction3": 0,
        "normalAction4": 0,
        "vitality": 87,
        "level": 12,
        "dummy0": 255
    },
    {
        "exp": 34200,
        "strength": 96,
        "agility": 67,
        "intelligence": 57,
        "luck": 52,
        "HP": 144,
        "MP": 42,
        "battleAction1": 0,
        "battleAction2": 0,
        "battleAction3": 0,
        "battleAction4": 0,
        "normalAction1": 0,
        "normalAction2": 0,
        "normalAction3": 0,
        "normalAction4": 0,
        "vitality": 87,
        "level": 13,
        "dummy0": 255
    },
    {
        "exp": 41907,
        "strength": 97,
        "agility": 68,
        "intelligence": 59,
        "luck": 55,
        "HP": 150,
        "MP": 45,
        "battleAction1": 2,
        "battleAction2": 0,
        "battleAction3": 0,
        "battleAction4": 0,
        "normalAction1": 0,
        "normalAction2": 0,
        "normalAction3": 0,
        "normalAction4": 0,
        "vitality": 87,
        "level": 14,
        "dummy0": 255
    },
    {
        "exp": 51546,
        "strength": 99,
        "agility": 69,
        "intelligence": 61,
        "luck": 59,
        "HP": 156,
        "MP": 48,
        "battleAction1": 0,
        "battleAction2": 0,
        "battleAction3": 0,
        "battleAction4": 0,
        "normalAction1": 0,
        "normalAction2": 0,
        "normalAction3": 0,
        "normalAction4": 0,
        "vitality": 88,
        "level": 15,
        "dummy0": 255
    },
    {
        "exp": 63597,
        "strength": 102,
        "agility": 71,
        "intelligence": 62,
        "luck": 60,
        "HP": 159,
        "MP": 50,
        "battleAction1": 0,
        "battleAction2": 0,
        "battleAction3": 0,
        "battleAction4": 0,
        "normalAction1": 0,
        "normalAction2": 0,
        "normalAction3": 0,
        "normalAction4": 0,
        "vitality": 88,
        "level": 16,
        "dummy0": 255
    },
    {
        "exp": 78661,
        "strength": 105,
        "agility": 73,
        "intelligence": 63,
        "luck": 62,
        "HP": 163,
        "MP": 52,
        "battleAction1": 0,
        "battleAction2": 0,
        "battleAction3": 0,
        "battleAction4": 0,
        "normalAction1": 0,
        "normalAction2": 0,
        "normalAction3": 0,
        "normalAction4": 0,
        "vitality": 88,
        "level": 17,
        "dummy0": 255
    },
    {
        "exp": 97496,
        "strength": 108,
        "agility": 76,
        "intelligence": 65,
        "luck": 64,
        "HP": 166,
        "MP": 54,
        "battleAction1": 0,
        "battleAction2": 0,
        "battleAction3": 0,
        "battleAction4": 0,
        "normalAction1": 0,
        "normalAction2": 0,
        "normalAction3": 0,
        "normalAction4": 0,
        "vitality": 88,
        "level": 18,
        "dummy0": 255
    },
    {
        "exp": 121045,
        "strength": 111,
        "agility": 78,
        "intelligence": 66,
        "luck": 66,
        "HP": 170,
        "MP": 56,
        "battleAction1": 0,
        "battleAction2": 0,
        "battleAction3": 0,
        "battleAction4": 0,
        "normalAction1": 0,
        "normalAction2": 0,
        "normalAction3": 0,
        "normalAction4": 0,
        "vitality": 88,
        "level": 19,
        "dummy0": 255
    },
    {
        "exp": 145329,
        "strength": 115,
        "agility": 81,
        "intelligence": 68,
        "luck": 68,
        "HP": 174,
        "MP": 59,
        "battleAction1": 21,
        "battleAction2": 0,
        "battleAction3": 0,
        "battleAction4": 0,
        "normalAction1": 0,
        "normalAction2": 0,
        "normalAction3": 0,
        "normalAction4": 0,
        "vitality": 88,
        "level": 20,
        "dummy0": 255
    },
    {
        "exp": 170373,
        "strength": 117,
        "agility": 81,
        "intelligence": 69,
        "luck": 69,
        "HP": 181,
        "MP": 60,
        "battleAction1": 0,
        "battleAction2": 0,
        "battleAction3": 0,
        "battleAction4": 0,
        "normalAction1": 0,
        "normalAction2": 0,
        "normalAction3": 0,
        "normalAction4": 0,
        "vitality": 88,
        "level": 21,
        "dummy0": 255
    },
    {
        "exp": 196199,
        "strength": 119,
        "agility": 81,
        "intelligence": 70,
        "luck": 71,
        "HP": 189,
        "MP": 62,
        "battleAction1": 0,
        "battleAction2": 0,
        "battleAction3": 0,
        "battleAction4": 0,
        "normalAction1": 135,
        "normalAction2": 0,
        "normalAction3": 0,
        "normalAction4": 0,
        "vitality": 88,
        "level": 22,
        "dummy0": 255
    },
    {
        "exp": 222834,
        "strength": 121,
        "agility": 82,
        "intelligence": 71,
        "luck": 73,
        "HP": 196,
        "MP": 63,
        "battleAction1": 0,
        "battleAction2": 0,
        "battleAction3": 0,
        "battleAction4": 0,
        "normalAction1": 0,
        "normalAction2": 0,
        "normalAction3": 0,
        "normalAction4": 0,
        "vitality": 88,
        "level": 23,
        "dummy0": 255
    },
    {
        "exp": 250302,
        "strength": 124,
        "agility": 82,
        "intelligence": 72,
        "luck": 75,
        "HP": 204,
        "MP": 65,
        "battleAction1": 0,
        "battleAction2": 0,
        "battleAction3": 0,
        "battleAction4": 0,
        "normalAction1": 0,
        "normalAction2": 0,
        "normalAction3": 0,
        "normalAction4": 0,
        "vitality": 88,
        "level": 24,
        "dummy0": 255
    },
    {
        "exp": 278629,
        "strength": 126,
        "agility": 83,
        "intelligence": 73,
        "luck": 77,
        "HP": 212,
        "MP": 66,
        "battleAction1": 0,
        "battleAction2": 0,
        "battleAction3": 0,
        "battleAction4": 0,
        "normalAction1": 0,
        "normalAction2": 0,
        "normalAction3": 0,
        "normalAction4": 0,
        "vitality": 88,
        "level": 25,
        "dummy0": 255
    },
    {
        "exp": 307842,
        "strength": 128,
        "agility": 83,
        "intelligence": 74,
        "luck": 79,
        "HP": 219,
        "MP": 68,
        "battleAction1": 0,
        "battleAction2": 0,
        "battleAction3": 0,
        "battleAction4": 0,
        "normalAction1": 0,
        "normalAction2": 0,
        "normalAction3": 0,
        "normalAction4": 0,
        "vitality": 88,
        "level": 26,
        "dummy0": 255
    },
    {
        "exp": 337968,
        "strength": 131,
        "agility": 83,
        "intelligence": 75,
        "luck": 81,
        "HP": 227,
        "MP": 69,
        "battleAction1": 80,
        "battleAction2": 0,
        "battleAction3": 0,
        "battleAction4": 0,
        "normalAction1": 0,
        "normalAction2": 0,
        "normalAction3": 0,
        "normalAction4": 0,
        "vitality": 88,
        "level": 27,
        "dummy0": 255
    },
    {
        "exp": 369036,
        "strength": 133,
        "agility": 84,
        "intelligence": 76,
        "luck": 83,
        "HP": 234,
        "MP": 71,
        "battleAction1": 0,
        "battleAction2": 0,
        "battleAction3": 0,
        "battleAction4": 0,
        "normalAction1": 0,
        "normalAction2": 0,
        "normalAction3": 0,
        "normalAction4": 0,
        "vitality": 88,
        "level": 28,
        "dummy0": 255
    },
    {
        "exp": 401075,
        "strength": 135,
        "agility": 84,
        "intelligence": 77,
        "luck": 85,
        "HP": 242,
        "MP": 72,
        "battleAction1": 0,
        "battleAction2": 0,
        "battleAction3": 0,
        "battleAction4": 0,
        "normalAction1": 0,
        "normalAction2": 0,
        "normalAction3": 0,
        "normalAction4": 0,
        "vitality": 88,
        "level": 29,
        "dummy0": 255
    },
    {
        "exp": 434116,
        "strength": 138,
        "agility": 85,
        "intelligence": 79,
        "luck": 87,
        "HP": 250,
        "MP": 74,
        "battleAction1": 3,
        "battleAction2": 0,
        "battleAction3": 0,
        "battleAction4": 0,
        "normalAction1": 0,
        "normalAction2": 0,
        "normalAction3": 0,
        "normalAction4": 0,
        "vitality": 89,
        "level": 30,
        "dummy0": 255
    },
    {
        "exp": 468190,
        "strength": 139,
        "agility": 85,
        "intelligence": 80,
        "luck": 89,
        "HP": 263,
        "MP": 76,
        "battleAction1": 0,
        "battleAction2": 0,
        "battleAction3": 0,
        "battleAction4": 0,
        "normalAction1": 0,
        "normalAction2": 0,
        "normalAction3": 0,
        "normalAction4": 0,
        "vitality": 89,
        "level": 31,
        "dummy0": 255
    },
    {
        "exp": 503330,
        "strength": 140,
        "agility": 85,
        "intelligence": 82,
        "luck": 91,
        "HP": 276,
        "MP": 79,
        "battleAction1": 0,
        "battleAction2": 0,
        "battleAction3": 0,
        "battleAction4": 0,
        "normalAction1": 0,
        "normalAction2": 0,
        "normalAction3": 0,
        "normalAction4": 0,
        "vitality": 89,
        "level": 32,
        "dummy0": 255
    },
    {
        "exp": 539568,
        "strength": 141,
        "agility": 85,
        "intelligence": 83,
        "luck": 93,
        "HP": 289,
        "MP": 81,
        "battleAction1": 0,
        "battleAction2": 0,
        "battleAction3": 0,
        "battleAction4": 0,
        "normalAction1": 0,
        "normalAction2": 0,
        "normalAction3": 0,
        "normalAction4": 0,
        "vitality": 89,
        "level": 33,
        "dummy0": 255
    },
    {
        "exp": 576939,
        "strength": 143,
        "agility": 85,
        "intelligence": 85,
        "luck": 95,
        "HP": 302,
        "MP": 84,
        "battleAction1": 0,
        "battleAction2": 0,
        "battleAction3": 0,
        "battleAction4": 0,
        "normalAction1": 0,
        "normalAction2": 0,
        "normalAction3": 0,
        "normalAction4": 0,
        "vitality": 89,
        "level": 34,
        "dummy0": 255
    },
    {
        "exp": 615479,
        "strength": 144,
        "agility": 85,
        "intelligence": 86,
        "luck": 98,
        "HP": 315,
        "MP": 87,
        "battleAction1": 0,
        "battleAction2": 0,
        "battleAction3": 0,
        "battleAction4": 0,
        "normalAction1": 0,
        "normalAction2": 0,
        "normalAction3": 0,
        "normalAction4": 0,
        "vitality": 89,
        "level": 35,
        "dummy0": 255
    },
    {
        "exp": 655223,
        "strength": 145,
        "agility": 85,
        "intelligence": 88,
        "luck": 100,
        "HP": 328,
        "MP": 89,
        "battleAction1": 0,
        "battleAction2": 0,
        "battleAction3": 0,
        "battleAction4": 0,
        "normalAction1": 0,
        "normalAction2": 0,
        "normalAction3": 0,
        "normalAction4": 0,
        "vitality": 89,
        "level": 36,
        "dummy0": 255
    },
    {
        "exp": 696210,
        "strength": 147,
        "agility": 85,
        "intelligence": 89,
        "luck": 102,
        "HP": 341,
        "MP": 92,
        "battleAction1": 0,
        "battleAction2": 0,
        "battleAction3": 0,
        "battleAction4": 0,
        "normalAction1": 0,
        "normalAction2": 0,
        "normalAction3": 0,
        "normalAction4": 0,
        "vitality": 89,
        "level": 37,
        "dummy0": 255
    },
    {
        "exp": 738478,
        "strength": 148,
        "agility": 85,
        "intelligence": 91,
        "luck": 104,
        "HP": 354,
        "MP": 94,
        "battleAction1": 0,
        "battleAction2": 0,
        "battleAction3": 0,
        "battleAction4": 0,
        "normalAction1": 0,
        "normalAction2": 0,
        "normalAction3": 0,
        "normalAction4": 0,
        "vitality": 89,
        "level": 38,
        "dummy0": 255
    },
    {
        "exp": 782068,
        "strength": 149,
        "agility": 85,
        "intelligence": 92,
        "luck": 106,
        "HP": 367,
        "MP": 97,
        "battleAction1": 0,
        "battleAction2": 0,
        "battleAction3": 0,
        "battleAction4": 0,
        "normalAction1": 0,
        "normalAction2": 0,
        "normalAction3": 0,
        "normalAction4": 0,
        "vitality": 89,
        "level": 39,
        "dummy0": 255
    },
    {
        "exp": 828384,
        "strength": 151,
        "agility": 86,
        "intelligence": 94,
        "luck": 109,
        "HP": 380,
        "MP": 100,
        "battleAction1": 0,
        "battleAction2": 0,
        "battleAction3": 0,
        "battleAction4": 0,
        "normalAction1": 0,
        "normalAction2": 0,
        "normalAction3": 0,
        "normalAction4": 0,
        "vitality": 89,
        "level": 40,
        "dummy0": 255
    },
    {
        "exp": 877595,
        "strength": 153,
        "agility": 86,
        "intelligence": 95,
        "luck": 111,
        "HP": 383,
        "MP": 102,
        "battleAction1": 0,
        "battleAction2": 0,
        "battleAction3": 0,
        "battleAction4": 0,
        "normalAction1": 0,
        "normalAction2": 0,
        "normalAction3": 0,
        "normalAction4": 0,
        "vitality": 89,
        "level": 41,
        "dummy0": 255
    },
    {
        "exp": 929883,
        "strength": 155,
        "agility": 86,
        "intelligence": 97,
        "luck": 113,
        "HP": 386,
        "MP": 104,
        "battleAction1": 0,
        "battleAction2": 0,
        "battleAction3": 0,
        "battleAction4": 0,
        "normalAction1": 0,
        "normalAction2": 0,
        "normalAction3": 0,
        "normalAction4": 0,
        "vitality": 89,
        "level": 42,
        "dummy0": 255
    },
    {
        "exp": 985440,
        "strength": 158,
        "agility": 86,
        "intelligence": 98,
        "luck": 115,
        "HP": 389,
        "MP": 106,
        "battleAction1": 0,
        "battleAction2": 0,
        "battleAction3": 0,
        "battleAction4": 0,
        "normalAction1": 0,
        "normalAction2": 0,
        "normalAction3": 0,
        "normalAction4": 0,
        "vitality": 89,
        "level": 43,
        "dummy0": 255
    },
    {
        "exp": 1044471,
        "strength": 160,
        "agility": 86,
        "intelligence": 100,
        "luck": 117,
        "HP": 392,
        "MP": 108,
        "battleAction1": 0,
        "battleAction2": 0,
        "battleAction3": 0,
        "battleAction4": 0,
        "normalAction1": 0,
        "normalAction2": 0,
        "normalAction3": 0,
        "normalAction4": 0,
        "vitality": 89,
        "level": 44,
        "dummy0": 255
    },
    {
        "exp": 1107191,
        "strength": 163,
        "agility": 86,
        "intelligence": 102,
        "luck": 119,
        "HP": 395,
        "MP": 110,
        "battleAction1": 0,
        "battleAction2": 0,
        "battleAction3": 0,
        "battleAction4": 0,
        "normalAction1": 0,
        "normalAction2": 0,
        "normalAction3": 0,
        "normalAction4": 0,
        "vitality": 89,
        "level": 45,
        "dummy0": 255
    },
    {
        "exp": 1173833,
        "strength": 165,
        "agility": 86,
        "intelligence": 103,
        "luck": 121,
        "HP": 398,
        "MP": 112,
        "battleAction1": 0,
        "battleAction2": 0,
        "battleAction3": 0,
        "battleAction4": 0,
        "normalAction1": 0,
        "normalAction2": 0,
        "normalAction3": 0,
        "normalAction4": 0,
        "vitality": 89,
        "level": 46,
        "dummy0": 255
    },
    {
        "exp": 1244641,
        "strength": 167,
        "agility": 86,
        "intelligence": 105,
        "luck": 123,
        "HP": 401,
        "MP": 114,
        "battleAction1": 0,
        "battleAction2": 0,
        "battleAction3": 0,
        "battleAction4": 0,
        "normalAction1": 0,
        "normalAction2": 0,
        "normalAction3": 0,
        "normalAction4": 0,
        "vitality": 89,
        "level": 47,
        "dummy0": 255
    },
    {
        "exp": 1319874,
        "strength": 170,
        "agility": 86,
        "intelligence": 106,
        "luck": 125,
        "HP": 404,
        "MP": 116,
        "battleAction1": 0,
        "battleAction2": 0,
        "battleAction3": 0,
        "battleAction4": 0,
        "normalAction1": 0,
        "normalAction2": 0,
        "normalAction3": 0,
        "normalAction4": 0,
        "vitality": 89,
        "level": 48,
        "dummy0": 255
    },
    {
        "exp": 1399810,
        "strength": 172,
        "agility": 86,
        "intelligence": 108,
        "luck": 127,
        "HP": 407,
        "MP": 118,
        "battleAction1": 0,
        "battleAction2": 0,
        "battleAction3": 0,
        "battleAction4": 0,
        "normalAction1": 0,
        "normalAction2": 0,
        "normalAction3": 0,
        "normalAction4": 0,
        "vitality": 89,
        "level": 49,
        "dummy0": 255
    },
    {
        "exp": 1502230,
        "strength": 175,
        "agility": 87,
        "intelligence": 110,
        "luck": 130,
        "HP": 410,
        "MP": 120,
        "battleAction1": 0,
        "battleAction2": 0,
        "battleAction3": 0,
        "battleAction4": 0,
        "normalAction1": 0,
        "normalAction2": 0,
        "normalAction3": 0,
        "normalAction4": 0,
        "vitality": 90,
        "level": 50,
        "dummy0": 255
    }
]