[
    {
        "exp": 0,
        "strength": 0,
        "agility": 0,
        "intelligence": 0,
        "luck": 0,
        "HP": 0,
        "MP": 0,
        "battleAction1": 0,
        "battleAction2": 0,
        "battleAction3": 0,
        "battleAction4": 0,
        "normalAction1": 0,
        "normalAction2": 0,
        "normalAction3": 0,
        "normalAction4": 0,
        "vitality": 0,
        "level": 0,
        "dummy0": 255
    },
    {
        "exp": 0,
        "strength": 79,
        "agility": 77,
        "intelligence": 62,
        "luck": 55,
        "HP": 143,
        "MP": 24,
        "battleAction1": 97,
        "battleAction2": 0,
        "battleAction3": 0,
        "battleAction4": 0,
        "normalAction1": 0,
        "normalAction2": 0,
        "normalAction3": 0,
        "normalAction4": 0,
        "vitality": 80,
        "level": 1,
        "dummy0": 255
    },
    {
        "exp": 210,
        "strength": 79,
        "agility": 77,
        "intelligence": 62,
        "luck": 55,
        "HP": 147,
        "MP": 24,
        "battleAction1": 0,
        "battleAction2": 0,
        "battleAction3": 0,
        "battleAction4": 0,
        "normalAction1": 0,
        "normalAction2": 0,
        "normalAction3": 0,
        "normalAction4": 0,
        "vitality": 80,
        "level": 2,
        "dummy0": 255
    },
    {
        "exp": 1050,
        "strength": 80,
        "agility": 78,
        "intelligence": 62,
        "luck": 56,
        "HP": 151,
        "MP": 24,
        "battleAction1": 0,
        "battleAction2": 0,
        "battleAction3": 0,
        "battleAction4": 0,
        "normalAction1": 0,
        "normalAction2": 0,
        "normalAction3": 0,
        "normalAction4": 0,
        "vitality": 80,
        "level": 3,
        "dummy0": 255
    },
    {
        "exp": 4410,
        "strength": 82,
        "agility": 78,
        "intelligence": 63,
        "luck": 56,
        "HP": 155,
        "MP": 24,
        "battleAction1": 0,
        "battleAction2": 0,
        "battleAction3": 0,
        "battleAction4": 0,
        "normalAction1": 0,
        "normalAction2": 0,
        "normalAction3": 0,
        "normalAction4": 0,
        "vitality": 80,
        "level": 4,
        "dummy0": 255
    },
    {
        "exp": 9030,
        "strength": 83,
        "agility": 79,
        "intelligence": 65,
        "luck": 57,
        "HP": 160,
        "MP": 24,
        "battleAction1": 38,
        "battleAction2": 0,
        "battleAction3": 0,
        "battleAction4": 0,
        "normalAction1": 0,
        "normalAction2": 0,
        "normalAction3": 0,
        "normalAction4": 0,
        "vitality": 82,
        "level": 5,
        "dummy0": 255
    },
    {
        "exp": 15382,
        "strength": 83,
        "agility": 79,
        "intelligence": 68,
        "luck": 57,
        "HP": 165,
        "MP": 24,
        "battleAction1": 0,
        "battleAction2": 0,
        "battleAction3": 0,
        "battleAction4": 0,
        "normalAction1": 0,
        "normalAction2": 0,
        "normalAction3": 0,
        "normalAction4": 0,
        "vitality": 82,
        "level": 6,
        "dummy0": 255
    },
    {
        "exp": 24123,
        "strength": 84,
        "agility": 79,
        "intelligence": 71,
        "luck": 57,
        "HP": 170,
        "MP": 24,
        "battleAction1": 0,
        "battleAction2": 0,
        "battleAction3": 0,
        "battleAction4": 0,
        "normalAction1": 0,
        "normalAction2": 0,
        "normalAction3": 0,
        "normalAction4": 0,
        "vitality": 83,
        "level": 7,
        "dummy0": 255
    },
    {
        "exp": 36147,
        "strength": 84,
        "agility": 79,
        "intelligence": 74,
        "luck": 57,
        "HP": 175,
        "MP": 24,
        "battleAction1": 59,
        "battleAction2": 0,
        "battleAction3": 0,
        "battleAction4": 0,
        "normalAction1": 125,
        "normalAction2": 0,
        "normalAction3": 0,
        "normalAction4": 0,
        "vitality": 85,
        "level": 8,
        "dummy0": 255
    },
    {
        "exp": 51177,
        "strength": 85,
        "agility": 79,
        "intelligence": 77,
        "luck": 57,
        "HP": 180,
        "MP": 25,
        "battleAction1": 0,
        "battleAction2": 0,
        "battleAction3": 0,
        "battleAction4": 0,
        "normalAction1": 0,
        "normalAction2": 0,
        "normalAction3": 0,
        "normalAction4": 0,
        "vitality": 87,
        "level": 9,
        "dummy0": 255
    },
    {
        "exp": 69964,
        "strength": 90,
        "agility": 80,
        "intelligence": 80,
        "luck": 57,
        "HP": 187,
        "MP": 25,
        "battleAction1": 0,
        "battleAction2": 0,
        "battleAction3": 0,
        "battleAction4": 0,
        "normalAction1": 0,
        "normalAction2": 0,
        "normalAction3": 0,
        "normalAction4": 0,
        "vitality": 90,
        "level": 10,
        "dummy0": 255
    },
    {
        "exp": 93452,
        "strength": 95,
        "agility": 81,
        "intelligence": 83,
        "luck": 58,
        "HP": 195,
        "MP": 26,
        "battleAction1": 0,
        "battleAction2": 0,
        "battleAction3": 0,
        "battleAction4": 0,
        "normalAction1": 0,
        "normalAction2": 0,
        "normalAction3": 0,
        "normalAction4": 0,
        "vitality": 92,
        "level": 11,
        "dummy0": 255
    },
    {
        "exp": 122815,
        "strength": 100,
        "agility": 82,
        "intelligence": 86,
        "luck": 59,
        "HP": 202,
        "MP": 27,
        "battleAction1": 0,
        "battleAction2": 0,
        "battleAction3": 0,
        "battleAction4": 0,
        "normalAction1": 0,
        "normalAction2": 0,
        "normalAction3": 0,
        "normalAction4": 0,
        "vitality": 95,
        "level": 12,
        "dummy0": 255
    },
    {
        "exp": 153095,
        "strength": 105,
        "agility": 83,
        "intelligence": 89,
        "luck": 60,
        "HP": 210,
        "MP": 27,
        "battleAction1": 0,
        "battleAction2": 0,
        "battleAction3": 0,
        "battleAction4": 0,
        "normalAction1": 0,
        "normalAction2": 0,
        "normalAction3": 0,
        "normalAction4": 0,
        "vitality": 99,
        "level": 13,
        "dummy0": 255
    },
    {
        "exp": 184321,
        "strength": 107,
        "agility": 84,
        "intelligence": 92,
        "luck": 61,
        "HP": 216,
        "MP": 28,
        "battleAction1": 0,
        "battleAction2": 0,
        "battleAction3": 0,
        "battleAction4": 0,
        "normalAction1": 0,
        "normalAction2": 0,
        "normalAction3": 0,
        "normalAction4": 0,
        "vitality": 103,
        "level": 14,
        "dummy0": 255
    },
    {
        "exp": 216524,
        "strength": 109,
        "agility": 85,
        "intelligence": 95,
        "luck": 62,
        "HP": 222,
        "MP": 28,
        "battleAction1": 0,
        "battleAction2": 0,
        "battleAction3": 0,
        "battleAction4": 0,
        "normalAction1": 0,
        "normalAction2": 0,
        "normalAction3": 0,
        "normalAction4": 0,
        "vitality": 107,
        "level": 15,
        "dummy0": 255
    },
    {
        "exp": 249733,
        "strength": 110,
        "agility": 86,
        "intelligence": 98,
        "luck": 63,
        "HP": 228,
        "MP": 28,
        "battleAction1": 0,
        "battleAction2": 0,
        "battleAction3": 0,
        "battleAction4": 0,
        "normalAction1": 0,
        "normalAction2": 0,
        "normalAction3": 0,
        "normalAction4": 0,
        "vitality": 113,
        "level": 16,
        "dummy0": 255
    },
    {
        "exp": 283981,
        "strength": 111,
        "agility": 87,
        "intelligence": 101,
        "luck": 64,
        "HP": 234,
        "MP": 29,
        "battleAction1": 0,
        "battleAction2": 0,
        "battleAction3": 0,
        "battleAction4": 0,
        "normalAction1": 0,
        "normalAction2": 0,
        "normalAction3": 0,
        "normalAction4": 0,
        "vitality": 119,
        "level": 17,
        "dummy0": 255
    },
    {
        "exp": 322512,
        "strength": 112,
        "agility": 89,
        "intelligence": 104,
        "luck": 65,
        "HP": 240,
        "MP": 29,
        "battleAction1": 0,
        "battleAction2": 0,
        "battleAction3": 0,
        "battleAction4": 0,
        "normalAction1": 130,
        "normalAction2": 0,
        "normalAction3": 0,
        "normalAction4": 0,
        "vitality": 120,
        "level": 18,
        "dummy0": 255
    },
    {
        "exp": 365860,
        "strength": 112,
        "agility": 90,
        "intelligence": 107,
        "luck": 66,
        "HP": 257,
        "MP": 29,
        "battleAction1": 0,
        "battleAction2": 0,
        "battleAction3": 0,
        "battleAction4": 0,
        "normalAction1": 0,
        "normalAction2": 0,
        "normalAction3": 0,
        "normalAction4": 0,
        "vitality": 121,
        "level": 19,
        "dummy0": 255
    },
    {
        "exp": 414627,
        "strength": 113,
        "agility": 92,
        "intelligence": 110,
        "luck": 67,
        "HP": 274,
        "MP": 30,
        "battleAction1": 27,
        "battleAction2": 0,
        "battleAction3": 0,
        "battleAction4": 0,
        "normalAction1": 0,
        "normalAction2": 0,
        "normalAction3": 0,
        "normalAction4": 0,
        "vitality": 122,
        "level": 20,
        "dummy0": 255
    },
    {
        "exp": 469491,
        "strength": 113,
        "agility": 93,
        "intelligence": 113,
        "luck": 68,
        "HP": 292,
        "MP": 38,
        "battleAction1": 0,
        "battleAction2": 0,
        "battleAction3": 0,
        "battleAction4": 0,
        "normalAction1": 0,
        "normalAction2": 0,
        "normalAction3": 0,
        "normalAction4": 0,
        "vitality": 124,
        "level": 21,
        "dummy0": 255
    },
    {
        "exp": 531215,
        "strength": 120,
        "agility": 95,
        "intelligence": 116,
        "luck": 69,
        "HP": 309,
        "MP": 46,
        "battleAction1": 0,
        "battleAction2": 0,
        "battleAction3": 0,
        "battleAction4": 0,
        "normalAction1": 0,
        "normalAction2": 0,
        "normalAction3": 0,
        "normalAction4": 0,
        "vitality": 125,
        "level": 22,
        "dummy0": 255
    },
    {
        "exp": 596797,
        "strength": 125,
        "agility": 97,
        "intelligence": 119,
        "luck": 70,
        "HP": 327,
        "MP": 56,
        "battleAction1": 0,
        "battleAction2": 0,
        "battleAction3": 0,
        "battleAction4": 0,
        "normalAction1": 0,
        "normalAction2": 0,
        "normalAction3": 0,
        "normalAction4": 0,
        "vitality": 127,
        "level": 23,
        "dummy0": 255
    },
    {
        "exp": 666479,
        "strength": 130,
        "agility": 97,
        "intelligence": 122,
        "luck": 71,
        "HP": 332,
        "MP": 66,
        "battleAction1": 0,
        "battleAction2": 0,
        "battleAction3": 0,
        "battleAction4": 0,
        "normalAction1": 0,
        "normalAction2": 0,
        "normalAction3": 0,
        "normalAction4": 0,
        "vitality": 129,
        "level": 24,
        "dummy0": 255
    },
    {
        "exp": 740518,
        "strength": 135,
        "agility": 98,
        "intelligence": 125,
        "luck": 72,
        "HP": 338,
        "MP": 76,
        "battleAction1": 0,
        "battleAction2": 0,
        "battleAction3": 0,
        "battleAction4": 0,
        "normalAction1": 0,
        "normalAction2": 0,
        "normalAction3": 0,
        "normalAction4": 0,
        "vitality": 131,
        "level": 25,
        "dummy0": 255
    },
    {
        "exp": 819186,
        "strength": 140,
        "agility": 98,
        "intelligence": 128,
        "luck": 73,
        "HP": 344,
        "MP": 86,
        "battleAction1": 0,
        "battleAction2": 0,
        "battleAction3": 0,
        "battleAction4": 0,
        "normalAction1": 0,
        "normalAction2": 0,
        "normalAction3": 0,
        "normalAction4": 0,
        "vitality": 133,
        "level": 26,
        "dummy0": 255
    },
    {
        "exp": 915065,
        "strength": 145,
        "agility": 99,
        "intelligence": 131,
        "luck": 75,
        "HP": 350,
        "MP": 96,
        "battleAction1": 0,
        "battleAction2": 0,
        "battleAction3": 0,
        "battleAction4": 0,
        "normalAction1": 0,
        "normalAction2": 0,
        "normalAction3": 0,
        "normalAction4": 0,
        "vitality": 136,
        "level": 27,
        "dummy0": 255
    },
    {
        "exp": 1031923,
        "strength": 148,
        "agility": 100,
        "intelligence": 134,
        "luck": 76,
        "HP": 366,
        "MP": 106,
        "battleAction1": 46,
        "battleAction2": 0,
        "battleAction3": 0,
        "battleAction4": 0,
        "normalAction1": 0,
        "normalAction2": 0,
        "normalAction3": 0,
        "normalAction4": 0,
        "vitality": 137,
        "level": 28,
        "dummy0": 255
    },
    {
        "exp": 1174349,
        "strength": 151,
        "agility": 101,
        "intelligence": 137,
        "luck": 78,
        "HP": 383,
        "MP": 116,
        "battleAction1": 0,
        "battleAction2": 0,
        "battleAction3": 0,
        "battleAction4": 0,
        "normalAction1": 0,
        "normalAction2": 0,
        "normalAction3": 0,
        "normalAction4": 0,
        "vitality": 138,
        "level": 29,
        "dummy0": 255
    },
    {
        "exp": 1316774,
        "strength": 155,
        "agility": 103,
        "intelligence": 140,
        "luck": 80,
        "HP": 400,
        "MP": 126,
        "battleAction1": 0,
        "battleAction2": 0,
        "battleAction3": 0,
        "battleAction4": 0,
        "normalAction1": 129,
        "normalAction2": 0,
        "normalAction3": 0,
        "normalAction4": 0,
        "vitality": 140,
        "level": 30,
        "dummy0": 255
    }
]